README.rst
setup.cfg
setup.py
CodeViking.contracts.egg-info/PKG-INFO
CodeViking.contracts.egg-info/SOURCES.txt
CodeViking.contracts.egg-info/dependency_links.txt
CodeViking.contracts.egg-info/namespace_packages.txt
CodeViking.contracts.egg-info/top_level.txt
codeviking/__init__.py
codeviking/contracts/__init__.py
codeviking/contracts/_version.py
codeviking/contracts/argcheckers.py
codeviking/contracts/conditions.py
codeviking/contracts/contracts.py
codeviking/contracts/decorator.py
codeviking/contracts/error.py
codeviking/contracts/switch.py
codeviking/contracts/types.py
test/test_DecoratorGroup.py
test/test_Switch.py
test/test_SwitchedDecorator.py
test/test_conditions.py
test/test_contract.py
test/test_make_arg_checker.py