Metadata-Version: 1.1
Name: CodeViking.contracts
Version: 0.15.0
Summary: Function and method call contracts
Home-page: https://bitbucket.org/codeviking/python-codeviking.contracts/
Author: Dan Bullok
Author-email: opensource@codeviking.com
License: MIT
Platform: any
Classifier: Development Status :: 4 - Beta
Classifier: Intended Audience :: Developers
Classifier: License :: OSI Approved
Classifier: License :: OSI Approved :: MIT License
Classifier: Natural Language :: English
Classifier: Operating System :: OS Independent
Classifier: Programming Language :: Python
Classifier: Programming Language :: Python :: 3
Classifier: Programming Language :: Python :: 3 :: Only
Classifier: Topic :: Software Development :: Libraries :: Python Modules
Classifier: Topic :: Software Development :: Quality Assurance
